configmodel/ConfigModel.py
configmodel/Decorators.py
configmodel/FieldBase.py
configmodel/Logger.py
configmodel/MixinCachedValues.py
configmodel/MixinDelayedWrite.py
configmodel/SerializerBase.py
configmodel/SerializerIni.py
configmodel/SerializersFactory.py
configmodel/Utils.py
configmodel/__init__.py
ConfigModel-0.2.1.dist-info/LICENSE.txt
ConfigModel-0.2.1.dist-info/METADATA
ConfigModel-0.2.1.dist-info/WHEEL
ConfigModel-0.2.1.dist-info/top_level.txt
ConfigModel-0.2.1.dist-info/RECORD
