Metadata-Version: 2.1
Name: ConfigModel
Version: 0.2.1
Summary: Allows defining model classes and loading/saving them to INI files
Home-page: https://github.com/umanamente/py-configmodel/
Author: Vasily Maslyukov
Author-email: auro.coding@gmail.com
License: MIT
Project-URL: Documentation, https://py-configmodel.readthedocs.io/
Project-URL: Source, https://github.com/umanamente/py-configmodel/
Project-URL: Changelog, https://py-configmodel.readthedocs.io/en/latest/changelog.html
Project-URL: Tracker, https://github.com/umanamente/py-configmodel/issues
Platform: any
Classifier: Development Status :: 4 - Beta
Classifier: Programming Language :: Python
License-File: LICENSE.txt
Requires-Dist: importlib-metadata ; python_version < "3.8"
Provides-Extra: testing
Requires-Dist: setuptools ; extra == 'testing'
Requires-Dist: pytest ; extra == 'testing'
Requires-Dist: pytest-cov ; extra == 'testing'
Requires-Dist: coverage ; extra == 'testing'
